<?xml version="1.0" ?>
<!DOCTYPE PubmedArticleSet PUBLIC "-//NLM//DTD PubMedArticle, 1st January 2017//EN" "https://dtd.nlm.nih.gov/ncbi/pubmed/out/pubmed_170101.dtd">
<PubmedArticleSet>
<PubmedArticle>
    <MedlineCitation Status="PubMed-not-MEDLINE" Owner="NLM">
        <PMID Version="1">26236224</PMID>
        <DateCreated>
            <Year>2015</Year>
            <Month>08</Month>
            <Day>03</Day>
        </DateCreated>
        <DateCompleted>
            <Year>2015</Year>
            <Month>08</Month>
            <Day>03</Day>
        </DateCompleted>
        <DateRevised>
            <Year>2017</Year>
            <Month>02</Month>
            <Day>20</Day>
        </DateRevised>
        <Article PubModel="Electronic-eCollection">
            <Journal>
                <JournalIssue CitedMedium="Print">
                    <Volume>9</Volume>
                    <PubDate>
                        <Year>2015</Year>
                    </PubDate>
                </JournalIssue>
                <Title>Frontiers in human neuroscience</Title>
                <ISOAbbreviation>Front Hum Neurosci</ISOAbbreviation>
            </Journal>
            <ArticleTitle>Predicting individual brain maturity using dynamic functional connectivity.</ArticleTitle>
            <Pagination>
                <MedlinePgn>418</MedlinePgn>
            </Pagination>
            <ELocationID EIdType="doi" ValidYN="Y">10.3389/fnhum.2015.00418</ELocationID>
            <Abstract>
                <AbstractText>Neuroimaging-based functional connectivity (FC) analyses have revealed significant developmental trends in specific intrinsic connectivity networks linked to cognitive and behavioral maturation. However, knowledge of how brain functional maturation is associated with FC dynamics at rest is limited. Here, we examined age-related differences in the temporal variability of FC dynamics with data publicly released by the Nathan Kline Institute (NKI; n = 183, ages 7-30) and showed that dynamic inter-region interactions can be used to accurately predict individual brain maturity across development. Furthermore, we identified a significant age-dependent trend underlying dynamic inter-network FC, including increasing variability of the connections between the visual network, default mode network (DMN) and cerebellum as well as within the cerebellum and DMN and decreasing variability within the cerebellum and between the cerebellum and DMN as well as the cingulo-opercular network. Overall, the results suggested significant developmental changes in dynamic inter-network interaction, which may shed new light on the functional organization of typical developmental brains.</AbstractText>
            </Abstract>
            <AuthorList CompleteYN="Y">
                <Author ValidYN="Y">
                    <LastName>Qin</LastName>
                    <ForeName>Jian</ForeName>
                    <Initials>J</Initials>
                    <AffiliationInfo>
                        <Affiliation>College of Mechatronics and Automation, National University of Defense Technology, Changsha China.</Affiliation>
                    </AffiliationInfo>
                </Author>
                <Author ValidYN="Y">
                    <LastName>Chen</LastName>
                    <ForeName>Shan-Guang</ForeName>
                    <Initials>SG</Initials>
                    <AffiliationInfo>
                        <Affiliation>National Key Laboratory of Human Factors Engineering, China Astronaut Research and Training Center, Beijing China.</Affiliation>
                    </AffiliationInfo>
                </Author>
                <Author ValidYN="Y">
                    <LastName>Hu</LastName>
                    <ForeName>Dewen</ForeName>
                    <Initials>D</Initials>
                    <AffiliationInfo>
                        <Affiliation>College of Mechatronics and Automation, National University of Defense Technology, Changsha China.</Affiliation>
                    </AffiliationInfo>
                </Author>
                <Author ValidYN="Y">
                    <LastName>Zeng</LastName>
                    <ForeName>Ling-Li</ForeName>
                    <Initials>LL</Initials>
                    <AffiliationInfo>
                        <Affiliation>College of Mechatronics and Automation, National University of Defense Technology, Changsha China.</Affiliation>
                    </AffiliationInfo>
                </Author>
                <Author ValidYN="Y">
                    <LastName>Fan</LastName>
                    <ForeName>Yi-Ming</ForeName>
                    <Initials>YM</Initials>
                    <AffiliationInfo>
                        <Affiliation>College of Mechatronics and Automation, National University of Defense Technology, Changsha China.</Affiliation>
                    </AffiliationInfo>
                </Author>
                <Author ValidYN="Y">
                    <LastName>Chen</LastName>
                    <ForeName>Xiao-Ping</ForeName>
                    <Initials>XP</Initials>
                    <AffiliationInfo>
                        <Affiliation>National Key Laboratory of Human Factors Engineering, China Astronaut Research and Training Center, Beijing China.</Affiliation>
                    </AffiliationInfo>
                </Author>
                <Author ValidYN="Y">
                    <LastName>Shen</LastName>
                    <ForeName>Hui</ForeName>
                    <Initials>H</Initials>
                    <AffiliationInfo>
                        <Affiliation>College of Mechatronics and Automation, National University of Defense Technology, Changsha China.</Affiliation>
                    </AffiliationInfo>
                </Author>
            </AuthorList>
            <Language>eng</Language>
            <PublicationTypeList>
                <PublicationType UI="D016428">Journal Article</PublicationType>
            </PublicationTypeList>
            <ArticleDate DateType="Electronic">
                <Year>2015</Year>
                <Month>07</Month>
                <Day>16</Day>
            </ArticleDate>
        </Article>
        <MedlineJournalInfo>
            <Country>Switzerland</Country>
            <MedlineTA>Front Hum Neurosci</MedlineTA>
            <NlmUniqueID>101477954</NlmUniqueID>
            <ISSNLinking>1662-5161</ISSNLinking>
        </MedlineJournalInfo>
        <CommentsCorrectionsList>
            <CommentsCorrections RefType="Cites">
                <RefSource>Nat Rev Neurosci. 2001 Jul;2(7):475-83</RefSource>
                <PMID Version="1">11433372</PMID>
            </CommentsCorrections>
            <CommentsCorrections RefType="Cites">
                <RefSource>Neuroreport. 2014 Dec 3;25(17):1344-9</RefSource>
                <PMID Version="1">25275678</PMID>
            </CommentsCorrections>
            <CommentsCorrections RefType="Cites">
                <RefSource>Neuroimage. 2014 Nov 15;102 Pt 2:345-57</RefSource>
                <PMID Version="1">25109530</PMID>
            </CommentsCorrections>
            <CommentsCorrections RefType="Cites">
                <RefSource>Hum Brain Mapp. 2009 Aug;30(8):2356-66</RefSource>
                <PMID Version="1">19172655</PMID>
            </CommentsCorrections>
            <CommentsCorrections RefType="Cites">
                <RefSource>Neuroimage. 2015 Jan 1;104:430-6</RefSource>
                <PMID Version="1">25234118</PMID>
            </CommentsCorrections>
            <CommentsCorrections RefType="Cites">
                <RefSource>Neuroimage. 2012 Mar;60(1):623-32</RefSource>
                <PMID Version="1">22233733</PMID>
            </CommentsCorrections>
            <CommentsCorrections RefType="Cites">
                <RefSource>PLoS One. 2009;4(4):e5226</RefSource>
                <PMID Version="1">19381298</PMID>
            </CommentsCorrections>
            <CommentsCorrections RefType="Cites">
                <RefSource>Cereb Cortex. 2010 Sep;20(9):2055-68</RefSource>
                <PMID Version="1">20032062</PMID>
            </CommentsCorrections>
            <CommentsCorrections RefType="Cites">
                <RefSource>Proc Natl Acad Sci U S A. 2007 Aug 14;104(33):13507-12</RefSource>
                <PMID Version="1">17679691</PMID>
            </CommentsCorrections>
            <CommentsCorrections RefType="Cites">
                <RefSource>Proc Natl Acad Sci U S A. 2013 Nov 12;110(46):18692-7</RefSource>
                <PMID Version="1">24167282</PMID>
            </CommentsCorrections>
            <CommentsCorrections RefType="Cites">
                <RefSource>Cereb Cortex. 2010 Jun;20(6):1432-47</RefSource>
                <PMID Version="1">19789183</PMID>
            </CommentsCorrections>
            <CommentsCorrections RefType="Cites">
                <RefSource>Cereb Cortex. 2014 Jul;24(7):1806-17</RefSource>
                <PMID Version="1">23395850</PMID>
            </CommentsCorrections>
            <CommentsCorrections RefType="Cites">
                <RefSource>Neuroimage. 2012 Jul 16;61(4):1059-66</RefSource>
                <PMID Version="1">22465841</PMID>
            </CommentsCorrections>
            <CommentsCorrections RefType="Cites">
                <RefSource>J Neurosci. 2011 Dec 14;31(50):18578-89</RefSource>
                <PMID Version="1">22171056</PMID>
            </CommentsCorrections>
            <CommentsCorrections RefType="Cites">
                <RefSource>Proc Natl Acad Sci U S A. 2014 Jul 15;111(28):10341-6</RefSource>
                <PMID Version="1">24982140</PMID>
            </CommentsCorrections>
            <CommentsCorrections RefType="Cites">
                <RefSource>Cereb Cortex. 2015 Jul;25(7):1987-99</RefSource>
                <PMID Version="1">24532319</PMID>
            </CommentsCorrections>
            <CommentsCorrections RefType="Cites">
                <RefSource>Proc Natl Acad Sci U S A. 2008 Mar 11;105(10):4028-32</RefSource>
                <PMID Version="1">18322013</PMID>
            </CommentsCorrections>
            <CommentsCorrections RefType="Cites">
                <RefSource>Neuroimage. 2014 Oct 15;100:471-80</RefSource>
                <PMID Version="1">24973603</PMID>
            </CommentsCorrections>
            <CommentsCorrections RefType="Cites">
                <RefSource>Proc Natl Acad Sci U S A. 2014 Apr 22;111(16):6058-62</RefSource>
                <PMID Version="1">24711399</PMID>
            </CommentsCorrections>
            <CommentsCorrections RefType="Cites">
                <RefSource>Neuroimage Clin. 2014 Jul 24;5:298-308</RefSource>
                <PMID Version="1">25161896</PMID>
            </CommentsCorrections>
            <CommentsCorrections RefType="Cites">
                <RefSource>Neuroimage. 2012 Jan 2;59(1):431-8</RefSource>
                <PMID Version="1">21810475</PMID>
            </CommentsCorrections>
            <CommentsCorrections RefType="Cites">
                <RefSource>PLoS Comput Biol. 2009 May;5(5):e1000381</RefSource>
                <PMID Version="1">19412534</PMID>
            </CommentsCorrections>
            <CommentsCorrections RefType="Cites">
                <RefSource>Ann N Y Acad Sci. 2004 Jun;1021:296-309</RefSource>
                <PMID Version="1">15251900</PMID>
            </CommentsCorrections>
            <CommentsCorrections RefType="Cites">
                <RefSource>Neuroimage. 2013 Oct 15;80:505-14</RefSource>
                <PMID Version="1">23631994</PMID>
            </CommentsCorrections>
            <CommentsCorrections RefType="Cites">
                <RefSource>Science. 2010 Sep 10;329(5997):1358-61</RefSource>
                <PMID Version="1">20829489</PMID>
            </CommentsCorrections>
            <CommentsCorrections RefType="Cites">
                <RefSource>Neuroimage. 2012 Mar;60(1):601-13</RefSource>
                <PMID Version="1">22227886</PMID>
            </CommentsCorrections>
            <CommentsCorrections RefType="Cites">
                <RefSource>Biol Psychiatry. 2010 Dec 15;68(12):1084-91</RefSource>
                <PMID Version="1">20728873</PMID>
            </CommentsCorrections>
            <CommentsCorrections RefType="Cites">
                <RefSource>Neuroimage. 2007 May 15;36(1):144-52</RefSource>
                <PMID Version="1">17434757</PMID>
            </CommentsCorrections>
            <CommentsCorrections RefType="Cites">
                <RefSource>Neuroimage. 2013 Oct 15;80:360-78</RefSource>
                <PMID Version="1">23707587</PMID>
            </CommentsCorrections>
            <CommentsCorrections RefType="Cites">
                <RefSource>J Neurosci. 2010 Jul 28;30(30):10243-50</RefSource>
                <PMID Version="1">20668207</PMID>
            </CommentsCorrections>
            <CommentsCorrections RefType="Cites">
                <RefSource>J Neurosci. 2011 Apr 27;31(17):6405-13</RefSource>
                <PMID Version="1">21525281</PMID>
            </CommentsCorrections>
            <CommentsCorrections RefType="Cites">
                <RefSource>Brain. 2012 May;135(Pt 5):1498-507</RefSource>
                <PMID Version="1">22418737</PMID>
            </CommentsCorrections>
            <CommentsCorrections RefType="Cites">
                <RefSource>Brain Connect. 2012;2(2):91-101</RefSource>
                <PMID Version="1">22559794</PMID>
            </CommentsCorrections>
            <CommentsCorrections RefType="Cites">
                <RefSource>Hum Brain Mapp. 2014 Feb;35(2):627-37</RefSource>
                <PMID Version="1">23125131</PMID>
            </CommentsCorrections>
            <CommentsCorrections RefType="Cites">
                <RefSource>Neuroimage. 2013 Oct 15;80:144-68</RefSource>
                <PMID Version="1">23702415</PMID>
            </CommentsCorrections>
            <CommentsCorrections RefType="Cites">
                <RefSource>PLoS One. 2012;7(6):e39731</RefSource>
                <PMID Version="1">22761880</PMID>
            </CommentsCorrections>
            <CommentsCorrections RefType="Cites">
                <RefSource>Cereb Cortex. 2011 Jan;21(1):145-54</RefSource>
                <PMID Version="1">20421249</PMID>
            </CommentsCorrections>
            <CommentsCorrections RefType="Cites">
                <RefSource>Neuroimage. 2010 Aug 1;52(1):290-301</RefSource>
                <PMID Version="1">20385244</PMID>
            </CommentsCorrections>
            <CommentsCorrections RefType="Cites">
                <RefSource>Cereb Cortex. 2009 Mar;19(3):640-57</RefSource>
                <PMID Version="1">18653667</PMID>
            </CommentsCorrections>
            <CommentsCorrections RefType="Cites">
                <RefSource>J Neurosci. 2010 Apr 7;30(14):4914-21</RefSource>
                <PMID Version="1">20371811</PMID>
            </CommentsCorrections>
            <CommentsCorrections RefType="Cites">
                <RefSource>Neuroimage. 2014 Jun;93 Pt 1:124-37</RefSource>
                <PMID Version="1">24560717</PMID>
            </CommentsCorrections>
            <CommentsCorrections RefType="Cites">
                <RefSource>Neuroimage. 2001 Aug;14(2):284-97</RefSource>
                <PMID Version="1">11467903</PMID>
            </CommentsCorrections>
            <CommentsCorrections RefType="Cites">
                <RefSource>J Psychiatr Res. 2014 Nov;58:89-95</RefSource>
                <PMID Version="1">25085608</PMID>
            </CommentsCorrections>
            <CommentsCorrections RefType="Cites">
                <RefSource>J Neurophysiol. 2010 Nov;104(5):2667-76</RefSource>
                <PMID Version="1">20844116</PMID>
            </CommentsCorrections>
            <CommentsCorrections RefType="Cites">
                <RefSource>J Neurosci. 2015 Apr 29;35(17):6849-59</RefSource>
                <PMID Version="1">25926460</PMID>
            </CommentsCorrections>
            <CommentsCorrections RefType="Cites">
                <RefSource>Neurobiol Aging. 2010 May;31(5):839-52</RefSource>
                <PMID Version="1">18674847</PMID>
            </CommentsCorrections>
            <CommentsCorrections RefType="Cites">
                <RefSource>Neuroimage. 2013 Nov 15;82:208-25</RefSource>
                <PMID Version="1">23747457</PMID>
            </CommentsCorrections>
            <CommentsCorrections RefType="Cites">
                <RefSource>Neuroimage. 2008 Jul 15;41(4):1493-503</RefSource>
                <PMID Version="1">18482851</PMID>
            </CommentsCorrections>
            <CommentsCorrections RefType="Cites">
                <RefSource>Cereb Cortex. 2007 Jul;17(7):1664-71</RefSource>
                <PMID Version="1">16963517</PMID>
            </CommentsCorrections>
            <CommentsCorrections RefType="Cites">
                <RefSource>PLoS Biol. 2009 Jul;7(7):e1000157</RefSource>
                <PMID Version="1">19621066</PMID>
            </CommentsCorrections>
            <CommentsCorrections RefType="Cites">
                <RefSource>Proc Natl Acad Sci U S A. 2013 Mar 12;110(11):4392-7</RefSource>
                <PMID Version="1">23440216</PMID>
            </CommentsCorrections>
            <CommentsCorrections RefType="Cites">
                <RefSource>Neuroimage. 2015 May 15;112:232-43</RefSource>
                <PMID Version="1">25731993</PMID>
            </CommentsCorrections>
            <CommentsCorrections RefType="Cites">
                <RefSource>Curr Opin Neurobiol. 2007 Apr;17(2):243-50</RefSource>
                <PMID Version="1">17321127</PMID>
            </CommentsCorrections>
            <CommentsCorrections RefType="Cites">
                <RefSource>Neuroimage. 2015 Jun;113:329-39</RefSource>
                <PMID Version="1">25776215</PMID>
            </CommentsCorrections>
            <CommentsCorrections RefType="Cites">
                <RefSource>Hum Brain Mapp. 2013 Sep;34(9):2154-77</RefSource>
                <PMID Version="1">22438275</PMID>
            </CommentsCorrections>
            <CommentsCorrections RefType="Cites">
                <RefSource>Cereb Cortex. 2012 Jan;22(1):158-65</RefSource>
                <PMID Version="1">21616982</PMID>
            </CommentsCorrections>
            <CommentsCorrections RefType="Cites">
                <RefSource>MAGMA. 2010 Dec;23(5-6):351-66</RefSource>
                <PMID Version="1">20162320</PMID>
            </CommentsCorrections>
            <CommentsCorrections RefType="Cites">
                <RefSource>Hum Brain Mapp. 2007 Nov;28(11):1163-77</RefSource>
                <PMID Version="1">17538951</PMID>
            </CommentsCorrections>
            <CommentsCorrections RefType="Cites">
                <RefSource>Neuroimage. 2012 Jul 16;61(4):931-40</RefSource>
                <PMID Version="1">22498657</PMID>
            </CommentsCorrections>
            <CommentsCorrections RefType="Cites">
                <RefSource>Neuroimage. 2010 Mar;50(1):81-98</RefSource>
                <PMID Version="1">20006716</PMID>
            </CommentsCorrections>
            <CommentsCorrections RefType="Cites">
                <RefSource>Neuroimage. 2011 Mar 1;55(1):287-95</RefSource>
                <PMID Version="1">21118724</PMID>
            </CommentsCorrections>
            <CommentsCorrections RefType="Cites">
                <RefSource>Neuroimage. 2015 May 15;112:86-95</RefSource>
                <PMID Version="1">25754068</PMID>
            </CommentsCorrections>
            <CommentsCorrections RefType="Cites">
                <RefSource>PLoS One. 2012;7(8):e44530</RefSource>
                <PMID Version="1">22952990</PMID>
            </CommentsCorrections>
            <CommentsCorrections RefType="Cites">
                <RefSource>PLoS Comput Biol. 2008 Jul 04;4(7):e1000106</RefSource>
                <PMID Version="1">18604265</PMID>
            </CommentsCorrections>
            <CommentsCorrections RefType="Cites">
                <RefSource>J Neurosci. 2015 Apr 8;35(14):5579-88</RefSource>
                <PMID Version="1">25855174</PMID>
            </CommentsCorrections>
            <CommentsCorrections RefType="Cites">
                <RefSource>J Neurosci. 2008 Apr 2;28(14):3586-94</RefSource>
                <PMID Version="1">18385317</PMID>
            </CommentsCorrections>
            <CommentsCorrections RefType="Cites">
                <RefSource>Neuroimage. 2007 Oct 1;37(4):1083-90; discussion 1097-9</RefSource>
                <PMID Version="1">17719799</PMID>
            </CommentsCorrections>
            <CommentsCorrections RefType="Cites">
                <RefSource>Front Neurosci. 2012 Oct 16;6:152</RefSource>
                <PMID Version="1">23087608</PMID>
            </CommentsCorrections>
            <CommentsCorrections RefType="Cites">
                <RefSource>Cereb Cortex. 2014 Mar;24(3):663-76</RefSource>
                <PMID Version="1">23146964</PMID>
            </CommentsCorrections>
            <CommentsCorrections RefType="Cites">
                <RefSource>Neuroimage. 2010 Feb 15;49(4):3110-21</RefSource>
                <PMID Version="1">19931396</PMID>
            </CommentsCorrections>
            <CommentsCorrections RefType="Cites">
                <RefSource>J Neurophysiol. 2011 Nov;106(5):2322-45</RefSource>
                <PMID Version="1">21795627</PMID>
            </CommentsCorrections>
        </CommentsCorrectionsList>
        <OtherID Source="NLM">PMC4503925</OtherID>
        <KeywordList Owner="NOTNLM">
            <Keyword MajorTopicYN="N">development</Keyword>
            <Keyword MajorTopicYN="N">fMRI</Keyword>
            <Keyword MajorTopicYN="N">functional connectivity</Keyword>
            <Keyword MajorTopicYN="N">low-frequency fluctuation</Keyword>
            <Keyword MajorTopicYN="N">multivariate pattern analysis</Keyword>
        </KeywordList>
    </MedlineCitation>
    <PubmedData>
        <History>
            <PubMedPubDate PubStatus="received">
                <Year>2015</Year>
                <Month>05</Month>
                <Day>09</Day>
            </PubMedPubDate>
            <PubMedPubDate PubStatus="accepted">
                <Year>2015</Year>
                <Month>07</Month>
                <Day>06</Day>
            </PubMedPubDate>
            <PubMedPubDate PubStatus="entrez">
                <Year>2015</Year>
                <Month>8</Month>
                <Day>4</Day>
                <Hour>6</Hour>
                <Minute>0</Minute>
            </PubMedPubDate>
            <PubMedPubDate PubStatus="pubmed">
                <Year>2015</Year>
                <Month>8</Month>
                <Day>4</Day>
                <Hour>6</Hour>
                <Minute>0</Minute>
            </PubMedPubDate>
            <PubMedPubDate PubStatus="medline">
                <Year>2015</Year>
                <Month>8</Month>
                <Day>4</Day>
                <Hour>6</Hour>
                <Minute>1</Minute>
            </PubMedPubDate>
        </History>
        <PublicationStatus>epublish</PublicationStatus>
        <ArticleIdList>
            <ArticleId IdType="pubmed">26236224</ArticleId>
            <ArticleId IdType="doi">10.3389/fnhum.2015.00418</ArticleId>
            <ArticleId IdType="pmc">PMC4503925</ArticleId>
        </ArticleIdList>
    </PubmedData>
</PubmedArticle>

</PubmedArticleSet>
