<?xml version="1.0" ?>
<!DOCTYPE PubmedArticleSet PUBLIC "-//NLM//DTD PubMedArticle, 1st January 2017//EN" "https://dtd.nlm.nih.gov/ncbi/pubmed/out/pubmed_170101.dtd">
<PubmedArticleSet>
<PubmedArticle>
    <MedlineCitation Status="Publisher" Owner="NLM">
        <PMID Version="1">24791032</PMID>
        <DateCreated>
            <Year>2014</Year>
            <Month>05</Month>
            <Day>02</Day>
        </DateCreated>
        <DateRevised>
            <Year>2017</Year>
            <Month>02</Month>
            <Day>20</Day>
        </DateRevised>
        <Article PubModel="Print">
            <Journal>
                <ISSN IssnType="Print">0162-1459</ISSN>
                <JournalIssue CitedMedium="Print">
                    <Volume>108</Volume>
                    <Issue>502</Issue>
                    <PubDate>
                        <Year>2013</Year>
                    </PubDate>
                </JournalIssue>
                <Title>Journal of the American Statistical Association</Title>
                <ISOAbbreviation>J Am Stat Assoc</ISOAbbreviation>
            </Journal>
            <ArticleTitle>Tensor Regression with Applications in Neuroimaging Data Analysis.</ArticleTitle>
            <Pagination>
                <MedlinePgn>540-552</MedlinePgn>
            </Pagination>
            <Abstract>
                <AbstractText>Classical regression methods treat covariates as a vector and estimate a corresponding vector of regression coefficients. Modern applications in medical imaging generate covariates of more complex form such as multidimensional arrays (tensors). Traditional statistical and computational methods are proving insufficient for analysis of these high-throughput data due to their ultrahigh dimensionality as well as complex structure. In this article, we propose a new family of tensor regression models that efficiently exploit the special structure of tensor covariates. Under this framework, ultrahigh dimensionality is reduced to a manageable level, resulting in efficient estimation and prediction. A fast and highly scalable estimation algorithm is proposed for maximum likelihood estimation and its associated asymptotic properties are studied. Effectiveness of the new methods is demonstrated on both synthetic and real MRI imaging data.</AbstractText>
            </Abstract>
            <AuthorList CompleteYN="Y">
                <Author ValidYN="Y">
                    <LastName>Zhou</LastName>
                    <ForeName>Hua</ForeName>
                    <Initials>H</Initials>
                    <AffiliationInfo>
                        <Affiliation>Department of Statistics, North Carolina State University, Raleigh, NC 27695-8203 ( hua zhou@ncsu.edu ).</Affiliation>
                    </AffiliationInfo>
                </Author>
                <Author ValidYN="Y">
                    <LastName>Li</LastName>
                    <ForeName>Lexin</ForeName>
                    <Initials>L</Initials>
                    <AffiliationInfo>
                        <Affiliation>Department of Statistics, North Carolina State University, Raleigh, NC 27695-8203.</Affiliation>
                    </AffiliationInfo>
                </Author>
                <Author ValidYN="Y">
                    <LastName>Zhu</LastName>
                    <ForeName>Hongtu</ForeName>
                    <Initials>H</Initials>
                    <AffiliationInfo>
                        <Affiliation>Department of Biostatistics and Biomedical Research Imaging Center, University of North Carolina, Chapel Hill, NC 27599-7420 ( hzhu@bios.unc.edu ).</Affiliation>
                    </AffiliationInfo>
                </Author>
            </AuthorList>
            <Language>eng</Language>
            <GrantList CompleteYN="Y">
                <Grant>
                    <GrantID>R01 HG006139</GrantID>
                    <Acronym>HG</Acronym>
                    <Agency>NHGRI NIH HHS</Agency>
                    <Country>United States</Country>
                </Grant>
                <Grant>
                    <GrantID>TL1 RR025745</GrantID>
                    <Acronym>RR</Acronym>
                    <Agency>NCRR NIH HHS</Agency>
                    <Country>United States</Country>
                </Grant>
                <Grant>
                    <GrantID>R01 MH086633</GrantID>
                    <Acronym>MH</Acronym>
                    <Agency>NIMH NIH HHS</Agency>
                    <Country>United States</Country>
                </Grant>
                <Grant>
                    <GrantID>UL1 RR025747</GrantID>
                    <Acronym>RR</Acronym>
                    <Agency>NCRR NIH HHS</Agency>
                    <Country>United States</Country>
                </Grant>
                <Grant>
                    <GrantID>P01 CA142538</GrantID>
                    <Acronym>CA</Acronym>
                    <Agency>NCI NIH HHS</Agency>
                    <Country>United States</Country>
                </Grant>
                <Grant>
                    <GrantID>KL2 RR025746</GrantID>
                    <Acronym>RR</Acronym>
                    <Agency>NCRR NIH HHS</Agency>
                    <Country>United States</Country>
                </Grant>
            </GrantList>
            <PublicationTypeList>
                <PublicationType UI="D016428">Journal Article</PublicationType>
            </PublicationTypeList>
        </Article>
        <MedlineJournalInfo>
            <Country>United States</Country>
            <MedlineTA>J Am Stat Assoc</MedlineTA>
            <NlmUniqueID>01510020R</NlmUniqueID>
            <ISSNLinking>0162-1459</ISSNLinking>
        </MedlineJournalInfo>
        <CommentsCorrectionsList>
            <CommentsCorrections RefType="Cites">
                <RefSource>J Am Stat Assoc. 2012;107(498):568-577</RefSource>
                <PMID Version="1">25400305</PMID>
            </CommentsCorrections>
            <CommentsCorrections RefType="Cites">
                <RefSource>Hum Brain Mapp. 2010 Jun;31(6):838-51</RefSource>
                <PMID Version="1">20496375</PMID>
            </CommentsCorrections>
            <CommentsCorrections RefType="Cites">
                <RefSource>Biol Psychiatry. 2007 Jun 15;61(12):1361-9</RefSource>
                <PMID Version="1">16950217</PMID>
            </CommentsCorrections>
            <CommentsCorrections RefType="Cites">
                <RefSource>Neuroimage. 2010 Jun;51(2):752-64</RefSource>
                <PMID Version="1">20188193</PMID>
            </CommentsCorrections>
            <CommentsCorrections RefType="Cites">
                <RefSource>J R Stat Soc Series B Stat Methodol. 2011 Sep;73(4):559-578</RefSource>
                <PMID Version="1">21860598</PMID>
            </CommentsCorrections>
            <CommentsCorrections RefType="Cites">
                <RefSource>Lancet. 2003 Nov 22;362(9397):1699-707</RefSource>
                <PMID Version="1">14643117</PMID>
            </CommentsCorrections>
            <CommentsCorrections RefType="Cites">
                <RefSource>Neuroimage. 2004;23 Suppl 1:S189-95</RefSource>
                <PMID Version="1">15501088</PMID>
            </CommentsCorrections>
            <CommentsCorrections RefType="Cites">
                <RefSource>Neuroimage. 2001 Dec;14(6):1361-9</RefSource>
                <PMID Version="1">11707092</PMID>
            </CommentsCorrections>
            <CommentsCorrections RefType="Cites">
                <RefSource>Neuroimage. 2008 Oct 15;43(1):44-58</RefSource>
                <PMID Version="1">18672070</PMID>
            </CommentsCorrections>
            <CommentsCorrections RefType="Cites">
                <RefSource>Science. 2009 Oct 16;326(5951):399-403</RefSource>
                <PMID Version="1">19833961</PMID>
            </CommentsCorrections>
            <CommentsCorrections RefType="Cites">
                <RefSource>IEEE Trans Syst Man Cybern B Cybern. 2007 Oct;37(5):1156-66</RefSource>
                <PMID Version="1">17926699</PMID>
            </CommentsCorrections>
            <CommentsCorrections RefType="Cites">
                <RefSource>Biometrics. 2010 Mar;66(1):61-9</RefSource>
                <PMID Version="1">19432766</PMID>
            </CommentsCorrections>
            <CommentsCorrections RefType="Cites">
                <RefSource>Neuroimage. 2010 Jul 1;51(3):1140-9</RefSource>
                <PMID Version="1">20227508</PMID>
            </CommentsCorrections>
            <CommentsCorrections RefType="Cites">
                <RefSource>Neuroimage. 2009 Oct 15;48(1):138-49</RefSource>
                <PMID Version="1">19481161</PMID>
            </CommentsCorrections>
            <CommentsCorrections RefType="Cites">
                <RefSource>Neuroimage. 2010 Aug 15;52(2):515-23</RefSource>
                <PMID Version="1">20420928</PMID>
            </CommentsCorrections>
            <CommentsCorrections RefType="Cites">
                <RefSource>Cereb Cortex. 2012 Sep;22(9):1993-2004</RefSource>
                <PMID Version="1">22038908</PMID>
            </CommentsCorrections>
        </CommentsCorrectionsList>
        <KeywordList Owner="NOTNLM">
            <Keyword MajorTopicYN="N">Brain imaging</Keyword>
            <Keyword MajorTopicYN="N">dimension reduction</Keyword>
            <Keyword MajorTopicYN="N">generalized linear model (GLM)</Keyword>
            <Keyword MajorTopicYN="N">magnetic resonance imaging (MRI)</Keyword>
            <Keyword MajorTopicYN="N">multidimensional array</Keyword>
            <Keyword MajorTopicYN="N">tensor regression</Keyword>
        </KeywordList>
    </MedlineCitation>
    <PubmedData>
        <History>
            <PubMedPubDate PubStatus="entrez">
                <Year>2014</Year>
                <Month>5</Month>
                <Day>3</Day>
                <Hour>6</Hour>
                <Minute>0</Minute>
            </PubMedPubDate>
            <PubMedPubDate PubStatus="pubmed">
                <Year>2013</Year>
                <Month>1</Month>
                <Day>1</Day>
                <Hour>0</Hour>
                <Minute>0</Minute>
            </PubMedPubDate>
            <PubMedPubDate PubStatus="medline">
                <Year>2013</Year>
                <Month>1</Month>
                <Day>1</Day>
                <Hour>0</Hour>
                <Minute>0</Minute>
            </PubMedPubDate>
        </History>
        <PublicationStatus>ppublish</PublicationStatus>
        <ArticleIdList>
            <ArticleId IdType="pubmed">24791032</ArticleId>
            <ArticleId IdType="doi">10.1080/01621459.2013.776499</ArticleId>
            <ArticleId IdType="pmc">PMC4004091</ArticleId>
            <ArticleId IdType="mid">NIHMS447658</ArticleId>
        </ArticleIdList>
        <?nihms?>
    </PubmedData>
</PubmedArticle>

</PubmedArticleSet>
